a_pandas_ex_html_view/LICENSE
a_pandas_ex_html_view/README.MD
a_pandas_ex_html_view/__init__.py
a_pandas_ex_html_view/requirements.txt
a_pandas_ex_html_view/thirdparty.json
a_pandas_ex_html_view-0.11.dist-info/LICENSE.rst
a_pandas_ex_html_view-0.11.dist-info/METADATA
a_pandas_ex_html_view-0.11.dist-info/WHEEL
a_pandas_ex_html_view-0.11.dist-info/top_level.txt
a_pandas_ex_html_view-0.11.dist-info/RECORD
