Metadata-Version: 2.1
Name: a-pandas-ex-html-view
Version: 0.11
Summary: View/save any Pandas DataFrame/Series as HTML, works with MultiIndex as well
Home-page: https://github.com/hansalemaos/a_pandas_ex_html_view
Author: Johannes Fischer
Author-email: aulasparticularesdealemaosp@gmail.com
License: MIT
Keywords: json,dict,list,HTML,CSS
Classifier: Development Status :: 4 - Beta
Classifier: Programming Language :: Python :: 3 :: Only
Classifier: Programming Language :: Python :: 3.10
Classifier: Topic :: Software Development :: Libraries :: Python Modules
Classifier: Topic :: Utilities
License-File: LICENSE.rst
Requires-Dist: a-pandas-ex-df-to-string
Requires-Dist: a-pandas-ex-plode-tool
Requires-Dist: pandas
Requires-Dist: regex
